euromod/__init__.py
euromod/base.py
euromod/container.py
euromod/core.py
euromod/euromod_cli.py
euromod/info.py
euromod/libs/BouncyCastle.Crypto.dll
euromod/libs/EM_Common.dll
euromod/libs/EM_Crypt.dll
euromod/libs/EM_Executable.dll
euromod/libs/EM_Transformer.dll
euromod/libs/EM_XmlHandler.dll
euromod/libs/Newtonsoft.Json.dll
euromod/libs/__init__.py
euromod/test/__init__.py
euromod/test/main.py
euromod/utils/__init__.py
euromod/utils/_paths.py
euromod/utils/clr_array_convert.py
euromod/utils/debug.py
euromod/utils/euromod_parsing.py
euromod/utils/utils.py
euromod-0.2.18.dist-info/licenses/LICENSE.txt
euromod-0.2.18.dist-info/licenses/NOTICE.txt
euromod-0.2.18.dist-info/METADATA
euromod-0.2.18.dist-info/WHEEL
euromod-0.2.18.dist-info/top_level.txt
euromod-0.2.18.dist-info/RECORD
