Metadata-Version: 2.4
Name: euromod
Version: 0.2.18
Summary: Run the microsimulation model EUROMOD. The latest model and software versions of EUROMOD are available at https://euromod-web.jrc.ec.europa.eu/download-euromod .
Author-email: Irina Belousova <iri.belousova@gmail.com>, Hannes Serruys <hannes.serruys@ec.europa.eu>
Maintainer-email: Hannes Serruys <hannes.serruys@ec.europa.eu>
License: # License 
Project-URL: Documentation, http://pythonconnectoreuromod.readthedocs.io/
Project-URL: GitHub, https://github.com/ec-jrc/pythonconnectoreuromod
Project-URL: Issues, https://github.com/ec-jrc/pythonconnectoreuromod/discussions
Project-URL: EUROMOD, https://euromod-web.jrc.ec.europa.eu/
Keywords: Euromod,Microsimulation
Classifier: Development Status :: 3 - Alpha
Classifier: Intended Audience :: Science/Research
Classifier: License :: Other/Proprietary License
Classifier: Operating System :: Microsoft
Classifier: Programming Language :: Python :: 3
Classifier: Topic :: Software Development :: Libraries :: Python Modules
Requires-Python: >=3.8
License-File: LICENSE.txt
License-File: NOTICE.txt
Requires-Dist: pandas
Requires-Dist: pythonnet
Requires-Dist: numpy
Requires-Dist: polars
Dynamic: license-file
